clearflow/__init__.py
clearflow/py.typed
clearflow-1.0.3.dist-info/METADATA
clearflow-1.0.3.dist-info/WHEEL
clearflow-1.0.3.dist-info/licenses/LICENSE
clearflow-1.0.3.dist-info/RECORD
