Metadata-Version: 2.4
Name: clearflow
Version: 1.0.3
Summary: Compose type-safe flows for emergent AI
Project-URL: Homepage, https://github.com/artificial-sapience/clearflow
Project-URL: Repository, https://github.com/artificial-sapience/clearflow.git
Project-URL: Source, https://github.com/artificial-sapience/clearflow
Project-URL: Issues, https://github.com/artificial-sapience/clearflow/issues
Project-URL: Examples, https://github.com/artificial-sapience/clearflow/tree/main/examples
Project-URL: Inspiration, https://github.com/The-Pocket/PocketFlow
Author-email: Richard Beauchamp <rbeauchamp@users.noreply.github.com>
Maintainer: ClearFlow Contributors
License-Expression: MIT
License-File: LICENSE
Keywords: agents,ai-agents,async,language-models,orchestration,reliable,type-safe,zero-dependencies
Classifier: Development Status :: 4 - Beta
Classifier: Intended Audience :: Developers
Classifier: License :: OSI Approved :: MIT License
Classifier: Operating System :: OS Independent
Classifier: Programming Language :: Python :: 3
Classifier: Programming Language :: Python :: 3.13
Classifier: Topic :: Scientific/Engineering :: Artificial Intelligence
Classifier: Topic :: Scientific/Engineering :: Information Analysis
Classifier: Topic :: Software Development :: Libraries :: Application Frameworks
Classifier: Topic :: Software Development :: Libraries :: Python Modules
Classifier: Topic :: Text Processing :: Linguistic
Classifier: Typing :: Typed
Requires-Python: >=3.13
Provides-Extra: dev
Requires-Dist: bandit[toml]>=1.8.0; extra == 'dev'
Requires-Dist: flake8-bugbear>=24.12.0; extra == 'dev'
Requires-Dist: pip-audit>=2.9.0; extra == 'dev'
Requires-Dist: pyright>=1.1.405; extra == 'dev'
Requires-Dist: pytest-asyncio>=1.1.0; extra == 'dev'
Requires-Dist: pytest-cov>=6.3.0; extra == 'dev'
Requires-Dist: pytest>=8.4.2; extra == 'dev'
Requires-Dist: radon>=6.0.1; extra == 'dev'
Requires-Dist: ruff>=0.12.0; extra == 'dev'
Requires-Dist: typeguard>=4.4.4; extra == 'dev'
Requires-Dist: vulture>=2.14; extra == 'dev'
Requires-Dist: xenon>=0.9.3; extra == 'dev'
Provides-Extra: examples
Requires-Dist: dspy>=3.0.3; extra == 'examples'
Requires-Dist: faiss-cpu>=1.12.0; extra == 'examples'
Requires-Dist: numpy>=2.3.0; extra == 'examples'
Requires-Dist: openai>=1.107.0; extra == 'examples'
Requires-Dist: pydantic>=2.11.0; extra == 'examples'
Requires-Dist: python-dotenv>=1.1.0; extra == 'examples'
Requires-Dist: rich>=13.7.1; extra == 'examples'
